mu_sqlalchemy_crud_helpers/__init__.py
mu_sqlalchemy_crud_helpers/crud_helpers.py
mu_sqlalchemy_crud_helpers-0.0.2.dist-info/LICENSE
mu_sqlalchemy_crud_helpers-0.0.2.dist-info/METADATA
mu_sqlalchemy_crud_helpers-0.0.2.dist-info/WHEEL
mu_sqlalchemy_crud_helpers-0.0.2.dist-info/top_level.txt
mu_sqlalchemy_crud_helpers-0.0.2.dist-info/RECORD
